bcontrolpy/__init__.py
bcontrolpy/bcontrolpy.py
bcontrolpy-0.0.5.dist-info/licenses/LICENSE
bcontrolpy-0.0.5.dist-info/METADATA
bcontrolpy-0.0.5.dist-info/WHEEL
bcontrolpy-0.0.5.dist-info/top_level.txt
bcontrolpy-0.0.5.dist-info/RECORD
