Metadata-Version: 2.4
Name: bcontrolpy
Version: 0.0.5
Summary: Python Modul zur Steuerung eines B-Control Webinterface
Author-email: ITTV-tools <ITTV-tools@users.noreply.github.com>
License: Apache License
Requires-Python: >=3.8
License-File: LICENSE
Requires-Dist: aiohttp>=3.8
Dynamic: license-file
